gracefml/__init__.py
gracefml/bounding/__init__.py
gracefml/bounding/bf.py
gracefml/datasets/__init__.py
gracefml/datasets/core.py
gracefml/datasets/data/boston_house_prices.gz
gracefml/types.py
gracefml-0.0.4.dist-info/LICENSE
gracefml-0.0.4.dist-info/WHEEL
gracefml-0.0.4.dist-info/METADATA
gracefml-0.0.4.dist-info/RECORD
